{
  "ver": "20160501.1",
  "list": [
    {
      "id": "A9YGyykQYpo",
      "title": "뽀빠이 1 - 자막 ",
      "ver": "20160501.1",
      "list": [
        {
          "id": "A9YGyykQYpo",
          "title": "1화 겁쟁이 뽀빠이(Scairdy Cat)",
          "duration": "5:44"
        },
        {
          "id": "Yga-JJ4rs6Y",
          "title": "2화 구조요원이 된 뽀빠이(Pepeye The Life Guard)",
          "duration": "5:53"
        },
        {
          "id": "yhi-hOceLSw",
          "title": "3화 늙은 나무 이야기(Spare Dat Tree)",
          "duration": "5:44"
        },
        {
          "id": "U77xIV7WwEA",
          "title": "4화 달콤한 완두콩 수프(Sweet Pea Soup)",
          "duration": "5:42"
        },
        {
          "id": "Q-S4ojPZbSQ",
          "title": "5화 댄스 경연대회(Popeye's Double Trouble)",
          "duration": "5:59"
        },
        {
          "id": "Eg97LV9mfIk",
          "title": "6화 두얼굴의 사나이(Two-Faced Paleface)",
          "duration": "5:40"
        },
        {
          "id": "anJUnuwZVpc",
          "title": "7화 로미오와 줄리엣(Love birds)",
          "duration": "5:40"
        },
        {
          "id": "LjGR66Zpevo",
          "title": "8화 마법구슬 쟁탈전(Crystal Ball Brawl)",
          "duration": "5:39"
        },
        {
          "id": "Aii5uNL-4Hg",
          "title": "9화 마법에 걸리다(Voo-Doo To You Too)",
          "duration": "5:44"
        },
        {
          "id": "skGfCCPuLeI",
          "title": "10화 마법의 시금치(Popeye And The Spinach Stalk)",
          "duration": "5:46"
        },
        {
          "id": "GDak767pib0",
          "title": "11화 마스크 오브 조로(The Mask Of Zero)",
          "duration": "5:44"
        },
        {
          "id": "BOnYkH1fyvw",
          "title": "12화 무서운 앨리스(Frozen Feuds)",
          "duration": "5:51"
        },
        {
          "id": "hawbt_jUDNA",
          "title": "13화 뮬러의 괴물 로봇(Mueller's Mad Monster)",
          "duration": "5:38"
        },
        {
          "id": "_zNvx4RZ7gs",
          "title": "14화 미사일 도시에서의 사고(Incident At Missile City)",
          "duration": "5:40"
        },
        {
          "id": "FG_mb55pX2k",
          "title": "15화 바다에서 만난 도둑(Sea No Evil)",
          "duration": "5:44"
        },
        {
          "id": "P_XDYb8UQUc",
          "title": "16화 배관공 뽀빠이의 꿈(Plumbers Pipe Dream)",
          "duration": "5:45"
        },
        {
          "id": "y6tuYOJCCus",
          "title": "17화 부부싸움(Insultin' The Sultan)",
          "duration": "5:53"
        },
        {
          "id": "NTRwDCBrLcs",
          "title": "18화 북극을 발견하다(Operation Ice-Tickle)",
          "duration": "5:38"
        },
        {
          "id": "EoJEyPAaWGM",
          "title": "19화 브루터스의 대형 슈퍼마켓(Super Duper Market)",
          "duration": "5:47"
        },
        {
          "id": "b4GqJmJ9XSQ",
          "title": "20화 브루터스의 주유소",
          "duration": "5:40"
        },
        {
          "id": "8P2IOQsud8k",
          "title": "21화 뽀빠이는 액션 배우(Matinee Idol Popeye)",
          "duration": "5:46"
        },
        {
          "id": "2sD4osG8FxI",
          "title": "22화 뽀빠이는 유식해(College Of Hard Knocks)",
          "duration": "5:38"
        },
        {
          "id": "hl3otSCI2WY",
          "title": "23화 뽀빠이는 트레이너(Popeye's Pep-up Emporium)",
          "duration": "5:44"
        },
        {
          "id": "tS1sErLZWfM",
          "title": "24화 뽀빠이의 세차장(Popeye's Car Wash)",
          "duration": "5:45"
        },
        {
          "id": "8x2TN7Dr7mQ",
          "title": "25화 뽀빠이의 신문사(What's News)",
          "duration": "5:41"
        },
        {
          "id": "GJ_Tdvh1lZg",
          "title": "26화 뽀빠이의 우주여행(Hit And Missiles)",
          "duration": "5:47"
        },
        {
          "id": "HPjxuoG56u4",
          "title": "27화 뽀빠이의 중고차(Popeye's Used Car)",
          "duration": "5:44"
        },
        {
          "id": "xH90qzSzt_Q",
          "title": "28화 사막에서 생긴일(Egypt Us)",
          "duration": "5:39"
        },
        {
          "id": "8v4RnAOE_KE",
          "title": "29화 아빠를 찾아서(Me Quest For Poopdeck Pappy)",
          "duration": "5:40"
        },
        {
          "id": "XqQJ-DNLhDU",
          "title": "30화 알라딘의 요술램프(Aladdin's Lamp)",
          "duration": "5:48"
        }
      ]
    },
    {
      "id": "sd-Zq8BBeOQ",
      "title": "뽀빠이 2 - 자막 ",
      "ver": "20160501.1",
      "list": [
        {
          "id": "sd-Zq8BBeOQ",
          "title": "31화 알프스에서의 휴가(The Big Sneeze)",
          "duration": "5:41"
        },
        {
          "id": "1WIm7aMxiY0",
          "title": "32화 약장사가 된 뽀빠이(The Medicine Man)",
          "duration": "5:43"
        },
        {
          "id": "JyEMXlm16Js",
          "title": "33화 올리브를 위하여(Duel To The Finish)",
          "duration": "5:43"
        },
        {
          "id": "f8YPhM5nBo8",
          "title": "34화 올리브의 다이어트(Weight For Me)",
          "duration": "5:40"
        },
        {
          "id": "6DoemWUZPgw",
          "title": "35화 올리브의 조카(Popeye's Junior Headache)",
          "duration": "5:47"
        },
        {
          "id": "3ppGELxvOVw",
          "title": "36화 운동경기(Track Meet Cheat)",
          "duration": "5:39"
        },
        {
          "id": "0WL21La3dGI",
          "title": "37화 웜피와 뽀빠이의 우정(Rags To Riches To Rags)",
          "duration": "5:38"
        },
        {
          "id": "INvc2UGvF6I",
          "title": "38화 웜피의 속임수(Wimpy The Moocher)",
          "duration": "5:39"
        },
        {
          "id": "cYvaEYfhywc",
          "title": "39화 유진 이야기(Jeep Tale)",
          "duration": "5:45"
        },
        {
          "id": "Kc0BIirQWyk",
          "title": "40화 주크박스(Wimpy's Lunch Wagon)",
          "duration": "5:45"
        },
        {
          "id": "cGT1MP_PJ9Q",
          "title": "41화 커피하우스에서(Coffee House)",
          "duration": "5:45"
        },
        {
          "id": "ZkufjLAyl00",
          "title": "42화 타임머신(Out Of This World)",
          "duration": "5:49"
        },
        {
          "id": "W88DwLV0q3s",
          "title": "43화 탁구 경기(After The Ball Went Over)",
          "duration": "5:43"
        },
        {
          "id": "07m0lq0jC9s",
          "title": "44화 패션사진(Fashion Foto Graphy)",
          "duration": "5:45"
        },
        {
          "id": "O9lO5oeADN4",
          "title": "45화 황금양모를 찾아서(Golden-Type fleece)",
          "duration": "5:47"
        }
      ]
    }
  ]
}