{
  "ver": "20160730.1",
  "list": [
    {
      "id": "KbPnP8HvzlE",
      "title": "로봇 알포",
      "ver": "20160730.1",
      "list": [
        {
          "id": "KbPnP8HvzlE",
          "title": "01   위대한 탄생",
          "duration": "10:57"
        },
        {
          "id": "xHsUkPRBq3Y",
          "title": "02   생방송! 도둑잡기!",
          "duration": "10:31"
        },
        {
          "id": "uSiL6uZAIc4",
          "title": "03   조이의 마법 대소동",
          "duration": "12:19"
        },
        {
          "id": "HcJIIhuA0Qc",
          "title": "04   이야기 좀비와 핫도그",
          "duration": "10:41"
        },
        {
          "id": "dI3DHWIqu9s",
          "title": "05   독감과의 전쟁",
          "duration": "11:35"
        },
        {
          "id": "xNHCjegHde0",
          "title": "06   완벽한 낮잠을 위하여",
          "duration": "11:15"
        },
        {
          "id": "XojNHlYLE7g",
          "title": "07   똑! 똑! 누구 없어요",
          "duration": "11:06"
        },
        {
          "id": "fyhdM6PrYNE",
          "title": "08화 비누방울 비행",
          "duration": "10:55"
        },
        {
          "id": "B9J_6n8QoWg",
          "title": "09   우유를 사수하라",
          "duration": "11:31"
        },
        {
          "id": "uEZKncU2Q14",
          "title": "10   충전이 필요해!",
          "duration": "10:53"
        },
        {
          "id": "40SIOzRt5YA",
          "title": "11   동물원 대소동",
          "duration": "11:38"
        },
        {
          "id": "CDqDtqaVH3E",
          "title": "12   로봇 대 로봇",
          "duration": "10:50"
        },
        {
          "id": "9kHGnADJTsM",
          "title": "13   광란의 스마트 홈",
          "duration": "10:25"
        },
        {
          "id": "O4ZRPI8rGJ8",
          "title": "14   다람쥐 포획 대작전",
          "duration": "10:23"
        },
        {
          "id": "BzpIzhEzkhw",
          "title": "15   소음을차단하라!",
          "duration": "10:22"
        },
        {
          "id": "ir4jUH6fWyw",
          "title": "16   투명로봇 되다!",
          "duration": "10:31"
        },
        {
          "id": "2kj_rv9BEuM",
          "title": "17   파워 업! 빨래 끝!",
          "duration": "10:16"
        },
        {
          "id": "8MEBcHl1dwU",
          "title": "18   젖꼭지 없인 못 살아!",
          "duration": "10:21"
        },
        {
          "id": "HeVON7dE87s",
          "title": "19   내 머리 속에 너 있다",
          "duration": "10:40"
        },
        {
          "id": "TlXOgOMTVyE",
          "title": "20 - 목욕은 즐거워!",
          "duration": "10:28"
        },
        {
          "id": "UotljDDlAJQ",
          "title": "21   헬리콥터를 낚아라",
          "duration": "10:22"
        },
        {
          "id": "tOZUsMaaq2A",
          "title": "22   꼭꼭 숨어라",
          "duration": "10:28"
        },
        {
          "id": "6XQjG8-shXM",
          "title": "23  다니엘, 개구리 왕 되다",
          "duration": "10:21"
        },
        {
          "id": "2ymUPLnUxdw",
          "title": "24  꿈꾸는 아기 다니엘",
          "duration": "10:42"
        },
        {
          "id": "QAXZIFghaKo",
          "title": "25 식탐 악어의 습격",
          "duration": "10:17"
        },
        {
          "id": "8N3a2fjg8-Q",
          "title": "26 불량 리모콘 대소동",
          "duration": "10:18"
        }
      ]
    }
  ]
}
