{
  "ver": "20160501.1",
  "list": [
    {
      "id": "vo5yr3TIers",
      "title": "지구용사 벡터맨 시즌1",
      "ver": "20160501.1",
      "list": [
        {
          "id": "vo5yr3TIers",
          "title": "OST - 레디아의 테마",
          "duration": "2:01"
        },
        {
          "id": "Bmz3WuOWsWw",
          "title": "4화",
          "duration": "23:18"
        },
        {
          "id": "bshQxUKd8sk",
          "title": "6화",
          "duration": "23:30"
        },
        {
          "id": "U9TJoZC0SLo",
          "title": "9화",
          "duration": "24:02"
        },
        {
          "id": "vdZ9OBWS8PY",
          "title": "10화",
          "duration": "23:16"
        },
        {
          "id": "dV4jQKU7PtM",
          "title": "13화",
          "duration": "23:09"
        },
        {
          "id": "9J-5oBViPR8",
          "title": "14화",
          "duration": "22:20"
        },
        {
          "id": "x2BA5UVB_zM",
          "title": "17화",
          "duration": "19:21"
        },
        {
          "id": "MmG-AyLG4Xg",
          "title": "19화1",
          "duration": "12:19"
        },
        {
          "id": "8TALoAKLmh8",
          "title": "19화2",
          "duration": "9:19"
        },
        {
          "id": "IkekQja56-w",
          "title": "20화",
          "duration": "22:25"
        },
        {
          "id": "buTJ1h5TZwM",
          "title": "21화",
          "duration": "22:36"
        },
        {
          "id": "cgzVHvg9pz0",
          "title": "24화",
          "duration": "22:32"
        },
        {
          "id": "Xr_y_VTwY-E",
          "title": "25화",
          "duration": "22:31"
        },
        {
          "id": "Q80D04mJgEo",
          "title": "최종",
          "duration": "22:43"
        },
        {
          "id": "m5xF1vMyIrw",
          "title": "사탄제국의 대역습",
          "duration": "1:17:9"
        }
      ]
    },
    {
      "id": "UfPdMp6FSMM",
      "title": "지구용사 벡터맨 시즌2",
      "ver": "20160501.1",
      "list": [
        {
          "id": "UfPdMp6FSMM",
          "title": "14화 (기태영, 김성수 출연)",
          "duration": "22:20"
        },
        {
          "id": "-Bv-u29SeSI",
          "title": "17화 (김성수 출연)",
          "duration": "19:21"
        },
        {
          "id": "smb4pB9PHQM",
          "title": "19화 (김성수, 신지수 출연)",
          "duration": "13:12"
        },
        {
          "id": "FmS9Ian-fVo",
          "title": "20화 (김성수, 엄지원 출연)",
          "duration": "22:25"
        },
        {
          "id": "7Dt8SHDYiDY",
          "title": "21화 (김성수, 엄지원 출연)",
          "duration": "22:36"
        },
        {
          "id": "PzO_tSkmCSM",
          "title": "24화 (김성수, 엄지원 출연)",
          "duration": "22:32"
        },
        {
          "id": "c6Q5xeI-H1k",
          "title": "25화 (김성수, 엄지원 출연)",
          "duration": "22:31"
        },
        {
          "id": "ojBlEWq9yKQ",
          "title": "최종 (김성수, 엄지원 출연)",
          "duration": "22:44"
        }
      ]
    }
  ]
}